bibliograpy/__init__.py
bibliograpy/api_bibtex.py
bibliograpy/api_common.py
bibliograpy/api_core.py
bibliograpy/api_endnote.py
bibliograpy/api_mesh.py
bibliograpy/api_pubmed.py
bibliograpy/api_refer.py
bibliograpy/api_ris2001.py
bibliograpy/api_ris2011.py
bibliograpy/bibliography.py
bibliograpy/bibliograpy.py
bibliograpy/default_symbolizer.py
bibliograpy/io_bibtex.py
bibliograpy/io_endnote.py
bibliograpy/io_pubmed.py
bibliograpy/io_refer.py
bibliograpy/io_ris2001.py
bibliograpy/io_ris2011.py
bibliograpy/process.py
bibliograpy-0.9.1.dist-info/licenses/LICENSE.md
bibliograpy-0.9.1.dist-info/METADATA
bibliograpy-0.9.1.dist-info/WHEEL
bibliograpy-0.9.1.dist-info/entry_points.txt
bibliograpy-0.9.1.dist-info/top_level.txt
bibliograpy-0.9.1.dist-info/RECORD
