Metadata-Version: 2.4
Name: bibliograpy
Version: 0.9.1
Author-email: Samuel Andrés <samuel.andres@yahoo.fr>
License: This is free and unencumbered software released into the public domain.
Project-URL: Homepage, https://github.com/SamuelAndresPascal/cosmoloj-py/tree/bibliograpy_0.9.1/bibliograpy
Project-URL: Documentation, http://cosmoloj.com/mkdocs/bibliograpy/en/0.9.1
Classifier: Programming Language :: Python :: 3
Classifier: Operating System :: OS Independent
Classifier: Development Status :: 5 - Production/Stable
Classifier: Intended Audience :: Developers
Classifier: License :: Public Domain
Classifier: Topic :: Software Development
Classifier: Topic :: Utilities
Requires-Python: >=3.12
License-File: LICENSE.md
Requires-Dist: pyyaml>=6
Requires-Dist: bibtexparser>=1.4.2
Dynamic: license-file
